reportxl/__init__.py
reportxl/sheet_table.py
reportxl-0.1.dist-info/LICENSE
reportxl-0.1.dist-info/METADATA
reportxl-0.1.dist-info/WHEEL
reportxl-0.1.dist-info/entry_points.txt
reportxl-0.1.dist-info/top_level.txt
reportxl-0.1.dist-info/RECORD
