Metadata-Version: 2.1
Name: reportxl
Version: 0.1
Summary: Use Excel to make a report.
Home-page: UNKNOWN
Author: Brendon Lin
Author-email: brendon.lin@outlook.com
License: UNKNOWN
Platform: UNKNOWN
Requires-Dist: openpyxl (>=3.0.5)
